airmac/setup.py
airmac-0.0.1.dist-info/licenses/LICENSE
airmac-0.0.1.dist-info/METADATA
airmac-0.0.1.dist-info/WHEEL
airmac-0.0.1.dist-info/top_level.txt
airmac-0.0.1.dist-info/RECORD
