Metadata-Version: 2.4
Name: airmac
Version: 0.0.1
Summary: A short description of the airmac package
Author-email: Cary Carter <ccarterdev@gmail.com>
License: MIT
Project-URL: Homepage, https://github.com/cc-d/airmac
Project-URL: Bug Tracker, https://github.com/cc-d/airmac/issues
Classifier: Programming Language :: Python :: 3
Classifier: License :: OSI Approved :: MIT License
Classifier: Operating System :: OS Independent
Requires-Python: >=3.6
License-File: LICENSE
Requires-Dist: pyobjc<11
Dynamic: license-file
